{"per_page":10,"total":16,"current":10,"data":[{"year":"2018","months":[{"month":"9","entries":[{"title":"Git解决冲突","date":"2018-09-27T18:04:55.000Z","link":"post/263"},{"title":"Java中的Double类型计算","date":"2018-09-14T03:07:00.000Z","link":"post/260"},{"title":"httpd启动错误和php项目访问空白页","date":"2018-09-12T06:42:57.000Z","link":"post/259"},{"title":"错误：java.sql.SQLException: The Network Adapter could not establish the connection","date":"2018-09-07T00:45:31.000Z","link":"post/258"},{"title":"JDK8 Lambda表达式——groupingby","date":"2018-09-05T02:03:00.000Z","link":"post/253"},{"title":"String字符串拼接","date":"2018-09-03T02:03:42.000Z","link":"post/250"},{"title":"Mybatis中关联查询和resultMap使用","date":"2018-09-02T03:40:55.000Z","link":"post/249"},{"title":"Mybatis中动态sql语句——ForEach语句","date":"2018-09-02T00:57:56.000Z","link":"post/248"},{"title":"Spring中的事物管理","date":"2018-09-01T22:35:00.000Z","link":"post/247"}]},{"month":"8","entries":[{"title":"idea运行错误Method breakpoints may dramatically slow down debugging","date":"2018-08-30T02:00:00.000Z","link":"post/246"}]}]}]}